{
  "parent": "",
  "dnid": "",
  "ot": "",
  "otid": "",
  "schtype": "",
  "task": "",
  "inherited": "",
  "state": "",
  "priority": "",
  "creur": "",
  "creurid": "",
  "creurcn": "",
  "cremail": "",
  "creempid": "",
  "cregrade": "",
  "credept": "",
  "credpid": "",
  "credpcd": "",
  "credate": "",
  "deldate": "",
  "subject": "",
  "location": "",
  "body": "",
  "periodfrom": "",
  "start": "",
  "periodto": "",
  "end": "",
  "term": "",
  "repeat": {
    "type": "",
    "end": "",
    "count": "",
    "intervaltype": "",
    "interval": "",
    "conday": "",
    "conweek": "",
    "condate": "",
    "rsvd1": "",
    "changeopt": "",
    "changedate": ""
  },
  "alarm": "",
  "rsvd1": "",
  "taskact": "",
  "cstate": "",
  "vdate": "",
  "cdate": "",
  "capprover": "",
  "partcount": "",
  "attachcount": "",
  "attachsize": "",
  "sharedcount": "",
  "cmntcount": "",
  "viewcount": "",
  "evalcount": "",
  "partlist": [],
  "attachlist": [],
  "sharedlist": [],
  "cmntlist": []
}